pptg-0.0.1.dist-info/METADATA
pptg-0.0.1.dist-info/WHEEL
pptg-0.0.1.dist-info/entry_points.txt
pptg-0.0.1.dist-info/licenses/LICENSE
pptg/__init__.py
pptg/__main__.py
pptg/__version__.py
pptg/main.py
pptg/package_data.dat
pptg-0.0.1.dist-info/RECORD
