Metadata-Version: 2.1
Name: pptg
Version: 0.0.1
Summary: A python package template to upload to pypi
Keywords: pdm template
Author-Email: lgf4591 <lgf4591@outlook.com>
License: MIT
Classifier: Development Status :: 4 - Beta
Classifier: License :: OSI Approved :: MIT License
Classifier: Programming Language :: Python :: 3.8
Classifier: Programming Language :: Python :: 3.9
Classifier: Programming Language :: Python :: 3.10
Classifier: Programming Language :: Python :: 3.11
Classifier: Programming Language :: Python :: 3.12
Project-URL: Homepage, https://github.com/lgf4591/pptg
Project-URL: Documentation, https://github.com/lgf4591/pptg/blob/master/README.md
Project-URL: Repository, https://github.com/lgf4591/pptg.git
Project-URL: Issues, https://github.com/lgf4591/pptg/issues
Project-URL: Changelog, https://github.com/lgf4591/pptg/blob/master/CHANGELOG.md
Requires-Python: >=3.8
Requires-Dist: importlib-metadata
